[{"sec":3.116883,"type":1},
{"sec":3.116883,"type":1},
{"sec":4.675325,"type":1},
{"sec":5.064935,"type":1},
{"sec":5.064935,"type":1},
{"sec":5.454545,"type":2},
{"sec":5.503247,"type":2},
{"sec":5.551948,"type":2},
{"sec":5.844156,"type":1},
{"sec":6.233766,"type":1},
{"sec":6.233766,"type":1},
{"sec":6.428571,"type":1},
{"sec":6.623377,"type":1},
{"sec":6.818182,"type":1},
{"sec":7.012987,"type":1},
{"sec":7.207792,"type":1},
{"sec":7.402597,"type":1},
{"sec":7.597403,"type":1},
{"sec":7.792208,"type":1},
{"sec":7.792208,"type":1},
{"sec":7.987013,"type":1},
{"sec":8.181818,"type":1},
{"sec":8.376623,"type":3},
{"sec":8.376623,"type":1},
{"sec":8.961039,"type":2},
{"sec":9.00974,"type":2},
{"sec":9.350649,"type":1},
{"sec":9.350649,"type":1},
{"sec":9.545455,"type":1},
{"sec":9.74026,"type":1},
{"sec":9.935065,"type":1},
{"sec":10.12987,"type":1},
{"sec":10.324675,"type":1},
{"sec":10.519481,"type":1},
{"sec":10.714286,"type":1},
{"sec":10.909091,"type":1},
{"sec":10.909091,"type":1},
{"sec":11.103896,"type":1},
{"sec":11.493506,"type":3},
{"sec":11.493506,"type":1},
{"sec":12.077922,"type":2},
{"sec":12.126623,"type":2},
{"sec":12.662338,"type":1},
{"sec":13.051948,"type":1},
{"sec":13.246753,"type":1},
{"sec":13.538961,"type":1},
{"sec":13.831169,"type":1},
{"sec":14.025974,"type":1},
{"sec":14.025974,"type":1},
{"sec":14.220779,"type":1},
{"sec":14.415584,"type":1},
{"sec":14.61039,"type":3},
{"sec":14.61039,"type":1},
{"sec":15,"type":1},
{"sec":15.38961,"type":1},
{"sec":15.38961,"type":1},
{"sec":15.779221,"type":1},
{"sec":15.974026,"type":1},
{"sec":16.168831,"type":3},
{"sec":16.168831,"type":1},
{"sec":16.558442,"type":1},
{"sec":16.948052,"type":1},
{"sec":16.948052,"type":1},
{"sec":17.337662,"type":1},
{"sec":17.532468,"type":1},
{"sec":17.727273,"type":3},
{"sec":17.727273,"type":1},
{"sec":18.116883,"type":1},
{"sec":18.506494,"type":1},
{"sec":18.506494,"type":1},
{"sec":18.896104,"type":1},
{"sec":19.090909,"type":1},
{"sec":19.285714,"type":3},
{"sec":19.285714,"type":1},
{"sec":19.675325,"type":1},
{"sec":20.064935,"type":1},
{"sec":20.064935,"type":1},
{"sec":20.454545,"type":1},
{"sec":20.649351,"type":1},
{"sec":20.844156,"type":1},
{"sec":20.844156,"type":1},
{"sec":21.233766,"type":1},
{"sec":21.623377,"type":1},
{"sec":21.623377,"type":1},
{"sec":22.012987,"type":1},
{"sec":22.207792,"type":1},
{"sec":22.402597,"type":3},
{"sec":22.402597,"type":1},
{"sec":22.792208,"type":1},
{"sec":23.181818,"type":1},
{"sec":23.376623,"type":1},
{"sec":23.571429,"type":1},
{"sec":23.766234,"type":1},
{"sec":23.961039,"type":2},
{"sec":24.00974,"type":2},
{"sec":24.350649,"type":2},
{"sec":24.399351,"type":2},
{"sec":24.74026,"type":2},
{"sec":24.788961,"type":2},
{"sec":24.837662,"type":2},
{"sec":24.935065,"type":2},
{"sec":25.519481,"type":1},
{"sec":25.616883,"type":1},
{"sec":25.714286,"type":1},
{"sec":25.974026,"type":1},
{"sec":26.233766,"type":1},
{"sec":26.493506,"type":3},
{"sec":26.493506,"type":1},
{"sec":26.883117,"type":3},
{"sec":27.077922,"type":1},
{"sec":27.272727,"type":3},
{"sec":27.662338,"type":1},
{"sec":27.857143,"type":1},
{"sec":28.051948,"type":1},
{"sec":28.831169,"type":3},
{"sec":28.831169,"type":1},
{"sec":28.928571,"type":1},
{"sec":29.025974,"type":1},
{"sec":29.123377,"type":1},
{"sec":29.220779,"type":1},
{"sec":29.415584,"type":1},
{"sec":29.61039,"type":1},
{"sec":29.61039,"type":1},
{"sec":29.805195,"type":1},
{"sec":30,"type":1},
{"sec":30.194805,"type":1},
{"sec":30.38961,"type":1},
{"sec":30.38961,"type":1},
{"sec":30.584416,"type":1},
{"sec":30.779221,"type":1},
{"sec":30.779221,"type":1},
{"sec":30.974026,"type":1},
{"sec":31.168831,"type":1},
{"sec":31.168831,"type":1},
{"sec":31.363636,"type":1},
{"sec":31.558442,"type":1},
{"sec":31.753247,"type":3},
{"sec":31.753247,"type":1},
{"sec":32.337662,"type":2},
{"sec":32.386364,"type":2},
{"sec":32.727273,"type":1},
{"sec":32.727273,"type":1},
{"sec":32.922078,"type":1},
{"sec":33.116883,"type":1},
{"sec":33.311688,"type":1},
{"sec":33.506494,"type":1},
{"sec":33.506494,"type":1},
{"sec":33.701299,"type":1},
{"sec":33.896104,"type":1},
{"sec":33.896104,"type":1},
{"sec":34.090909,"type":1},
{"sec":34.285714,"type":1},
{"sec":34.285714,"type":1},
{"sec":34.480519,"type":1},
{"sec":34.87013,"type":3},
{"sec":34.87013,"type":1},
{"sec":35.25974,"type":2},
{"sec":35.454545,"type":2},
{"sec":35.503247,"type":2},
{"sec":35.844156,"type":1},
{"sec":35.844156,"type":1},
{"sec":36.233766,"type":1},
{"sec":36.623377,"type":1},
{"sec":36.818182,"type":1},
{"sec":36.915584,"type":1},
{"sec":37.012987,"type":1},
{"sec":37.207792,"type":1},
{"sec":37.402597,"type":1},
{"sec":37.402597,"type":1},
{"sec":37.597403,"type":1},
{"sec":37.792208,"type":1},
{"sec":37.987013,"type":1},
{"sec":37.987013,"type":1},
{"sec":38.376623,"type":1},
{"sec":38.571429,"type":1},
{"sec":38.766234,"type":1},
{"sec":38.961039,"type":1},
{"sec":39.350649,"type":1},
{"sec":39.350649,"type":1},
{"sec":39.74026,"type":1},
{"sec":40.12987,"type":1},
{"sec":40.12987,"type":1},
{"sec":40.519481,"type":1},
{"sec":40.714286,"type":3},
{"sec":40.909091,"type":3},
{"sec":41.103896,"type":1},
{"sec":41.103896,"type":3},
{"sec":41.688312,"type":2},
{"sec":41.737013,"type":2},
{"sec":42.077922,"type":1},
{"sec":42.077922,"type":1},
{"sec":42.467532,"type":1},
{"sec":42.857143,"type":1},
{"sec":43.051948,"type":1},
{"sec":43.149351,"type":1},
{"sec":43.246753,"type":1},
{"sec":43.441558,"type":1},
{"sec":43.636364,"type":1},
{"sec":43.636364,"type":1},
{"sec":43.831169,"type":1},
{"sec":44.025974,"type":1},
{"sec":44.220779,"type":1},
{"sec":44.220779,"type":1},
{"sec":44.61039,"type":1},
{"sec":44.805195,"type":1},
{"sec":45,"type":1},
{"sec":45.194805,"type":1},
{"sec":45.584416,"type":1},
{"sec":45.584416,"type":1},
{"sec":45.974026,"type":1},
{"sec":46.266234,"type":1},
{"sec":46.363636,"type":1},
{"sec":46.558442,"type":1},
{"sec":46.753247,"type":1},
{"sec":46.753247,"type":1},
{"sec":46.948052,"type":1},
{"sec":47.142857,"type":1},
{"sec":47.337662,"type":3},
{"sec":47.727273,"type":3},
{"sec":47.727273,"type":1},
{"sec":47.922078,"type":1},
{"sec":48.116883,"type":3},
{"sec":48.506494,"type":3},
{"sec":48.506494,"type":1},
{"sec":48.701299,"type":1},
{"sec":48.896104,"type":3},
{"sec":49.285714,"type":3},
{"sec":49.285714,"type":1},
{"sec":49.480519,"type":1},
{"sec":49.87013,"type":3},
{"sec":49.87013,"type":1},
{"sec":50.454545,"type":1},
{"sec":50.649351,"type":3},
{"sec":50.649351,"type":1},
{"sec":51.038961,"type":1},
{"sec":51.038961,"type":1},
{"sec":51.428571,"type":3},
{"sec":51.428571,"type":1},
{"sec":51.818182,"type":3},
{"sec":52.012987,"type":1},
{"sec":52.012987,"type":1},
{"sec":52.207792,"type":1},
{"sec":52.597403,"type":1},
{"sec":52.597403,"type":1},
{"sec":52.987013,"type":1},
{"sec":52.987013,"type":1},
{"sec":53.376623,"type":1},
{"sec":53.571429,"type":1},
{"sec":53.571429,"type":1},
{"sec":53.766234,"type":1},
{"sec":54.155844,"type":1},
{"sec":54.155844,"type":1},
{"sec":54.545455,"type":1},
{"sec":54.935065,"type":1},
{"sec":55.12987,"type":1},
{"sec":55.12987,"type":1},
{"sec":55.324675,"type":1},
{"sec":55.519481,"type":1},
{"sec":55.616883,"type":1},
{"sec":55.714286,"type":1},
{"sec":56.103896,"type":3},
{"sec":56.103896,"type":1},
{"sec":56.688312,"type":1},
{"sec":56.883117,"type":3},
{"sec":56.883117,"type":1},
{"sec":57.272727,"type":1},
{"sec":57.272727,"type":1},
{"sec":57.662338,"type":3},
{"sec":57.662338,"type":1},
{"sec":58.051948,"type":3},
{"sec":58.246753,"type":1},
{"sec":58.246753,"type":1},
{"sec":58.441558,"type":1},
{"sec":58.831169,"type":1},
{"sec":58.831169,"type":1},
{"sec":59.220779,"type":1},
{"sec":59.220779,"type":1},
{"sec":59.805195,"type":1},
{"sec":59.805195,"type":1},
{"sec":60,"type":1},
{"sec":60.194805,"type":1},
{"sec":60.38961,"type":1},
{"sec":60.584416,"type":1},
{"sec":60.779221,"type":1},
{"sec":60.974026,"type":1},
{"sec":61.168831,"type":1},
{"sec":61.168831,"type":1},
{"sec":61.558442,"type":1},
{"sec":61.558442,"type":1},
{"sec":61.948052,"type":1},
{"sec":61.948052,"type":1},
{"sec":62.337662,"type":3},
{"sec":62.337662,"type":1},
{"sec":62.922078,"type":1},
{"sec":63.116883,"type":3},
{"sec":63.116883,"type":1},
{"sec":63.506494,"type":1},
{"sec":63.896104,"type":3},
{"sec":63.896104,"type":1},
{"sec":64.285714,"type":3},
{"sec":64.480519,"type":1},
{"sec":64.480519,"type":1},
{"sec":64.675325,"type":1},
{"sec":65.064935,"type":1},
{"sec":65.454545,"type":1},
{"sec":65.454545,"type":1},
{"sec":65.649351,"type":1},
{"sec":66.038961,"type":3},
{"sec":66.038961,"type":1},
{"sec":66.428571,"type":1},
{"sec":66.623377,"type":2},
{"sec":66.672078,"type":2},
{"sec":67.012987,"type":1},
{"sec":67.012987,"type":1},
{"sec":67.207792,"type":3},
{"sec":67.402597,"type":3},
{"sec":67.597403,"type":3},
{"sec":67.597403,"type":1},
{"sec":67.987013,"type":1},
{"sec":68.181818,"type":2},
{"sec":68.230519,"type":2},
{"sec":68.571429,"type":1},
{"sec":68.766234,"type":1},
{"sec":68.961039,"type":1},
{"sec":68.961039,"type":2},
{"sec":69.00974,"type":2},
{"sec":69.350649,"type":1},
{"sec":69.545455,"type":1},
{"sec":69.74026,"type":1},
{"sec":69.74026,"type":2},
{"sec":69.788961,"type":2},
{"sec":70.12987,"type":1},
{"sec":70.324675,"type":1},
{"sec":70.519481,"type":1},
{"sec":70.519481,"type":2},
{"sec":70.568182,"type":2},
{"sec":70.909091,"type":1},
{"sec":71.103896,"type":1},
{"sec":71.298701,"type":1},
{"sec":71.298701,"type":2},
{"sec":71.347403,"type":2},
{"sec":71.688312,"type":1},
{"sec":71.688312,"type":1},
{"sec":71.883117,"type":1},
{"sec":72.077922,"type":3},
{"sec":72.467532,"type":3},
{"sec":72.467532,"type":1},
{"sec":72.662338,"type":1},
{"sec":72.857143,"type":3},
{"sec":73.246753,"type":3},
{"sec":73.246753,"type":1},
{"sec":73.441558,"type":1},
{"sec":73.636364,"type":1},
{"sec":73.831169,"type":1},
{"sec":74.220779,"type":1},
{"sec":74.61039,"type":1},
{"sec":74.805195,"type":3},
{"sec":74.805195,"type":3},
{"sec":75.584416,"type":3},
{"sec":75.779221,"type":2},
{"sec":75.974026,"type":2},
{"sec":76.168831,"type":2},
{"sec":76.168831,"type":2},
{"sec":76.217532,"type":2},
{"sec":76.558442,"type":1},
{"sec":76.948052,"type":1},
{"sec":77.142857,"type":1},
{"sec":77.435065,"type":1},
{"sec":77.727273,"type":1},
{"sec":77.922078,"type":1},
{"sec":77.922078,"type":1},
{"sec":78.116883,"type":1},
{"sec":78.311688,"type":1},
{"sec":78.506494,"type":3},
{"sec":78.506494,"type":3},
{"sec":78.896104,"type":1},
{"sec":78.896104,"type":1},
{"sec":79.285714,"type":1},
{"sec":79.285714,"type":1},
{"sec":79.675325,"type":1},
{"sec":79.87013,"type":1},
{"sec":80.064935,"type":3},
{"sec":80.064935,"type":3},
{"sec":80.454545,"type":1},
{"sec":80.454545,"type":1},
{"sec":80.844156,"type":1},
{"sec":80.844156,"type":1},
{"sec":81.233766,"type":1},
{"sec":81.428571,"type":1},
{"sec":81.623377,"type":3},
{"sec":81.623377,"type":3},
{"sec":82.012987,"type":1},
{"sec":82.012987,"type":1},
{"sec":82.402597,"type":1},
{"sec":82.402597,"type":1},
{"sec":82.792208,"type":1},
{"sec":82.987013,"type":1},
{"sec":83.181818,"type":3},
{"sec":83.181818,"type":3},
{"sec":83.571429,"type":1},
{"sec":83.571429,"type":1},
{"sec":83.961039,"type":1},
{"sec":83.961039,"type":1},
{"sec":84.350649,"type":1},
{"sec":84.545455,"type":1},
{"sec":84.74026,"type":3},
{"sec":84.74026,"type":3},
{"sec":85.12987,"type":1},
{"sec":85.12987,"type":1},
{"sec":85.519481,"type":1},
{"sec":85.519481,"type":1},
{"sec":85.909091,"type":3},
{"sec":86.103896,"type":3},
{"sec":86.298701,"type":3},
{"sec":86.298701,"type":3},
{"sec":86.688312,"type":1},
{"sec":86.688312,"type":1},
{"sec":87.077922,"type":1},
{"sec":87.272727,"type":1},
{"sec":87.467532,"type":1},
{"sec":87.662338,"type":1},
{"sec":87.857143,"type":2},
{"sec":87.905844,"type":2},
{"sec":88.246753,"type":2},
{"sec":88.295455,"type":2},
{"sec":88.636364,"type":2},
{"sec":88.685065,"type":2},
{"sec":88.733766,"type":2},
{"sec":88.831169,"type":2},
{"sec":89.090909,"type":1},
{"sec":89.350649,"type":1},
{"sec":89.61039,"type":1},
{"sec":89.87013,"type":1},
{"sec":90.12987,"type":1},
{"sec":90.38961,"type":1},
{"sec":90.38961,"type":1},
{"sec":90.584416,"type":1},
{"sec":90.584416,"type":1},
{"sec":90.779221,"type":1},
{"sec":90.779221,"type":1},
{"sec":90.974026,"type":3},
{"sec":90.974026,"type":3},
{"sec":91.363636,"type":1},
{"sec":91.363636,"type":1},
{"sec":91.753247,"type":1},
{"sec":91.753247,"type":1},
{"sec":92.142857,"type":1},
{"sec":92.142857,"type":1},
{"sec":92.337662,"type":1},
{"sec":92.337662,"type":1},
{"sec":92.532468,"type":3},
{"sec":92.532468,"type":3},
{"sec":92.922078,"type":1},
{"sec":92.922078,"type":1},
{"sec":93.311688,"type":1},
{"sec":93.311688,"type":1},
{"sec":93.701299,"type":1},
{"sec":93.701299,"type":1},
{"sec":93.896104,"type":1},
{"sec":93.896104,"type":1},
{"sec":94.090909,"type":3},
{"sec":94.090909,"type":3},
{"sec":94.480519,"type":1},
{"sec":94.480519,"type":1},
{"sec":94.87013,"type":1},
{"sec":94.87013,"type":1},
{"sec":95.25974,"type":1},
{"sec":95.25974,"type":1},
{"sec":95.454545,"type":1},
{"sec":95.454545,"type":1},
{"sec":95.649351,"type":3},
{"sec":95.649351,"type":3},
{"sec":96.038961,"type":1},
{"sec":96.038961,"type":1},
{"sec":96.428571,"type":1},
{"sec":96.428571,"type":1},
{"sec":96.818182,"type":1},
{"sec":96.818182,"type":1},
{"sec":97.012987,"type":1},
{"sec":97.012987,"type":1},
{"sec":97.207792,"type":1},
{"sec":97.207792,"type":1},
{"sec":97.597403,"type":1},
{"sec":97.597403,"type":1},
{"sec":97.987013,"type":1},
{"sec":97.987013,"type":1},
{"sec":98.376623,"type":1},
{"sec":98.376623,"type":1},
{"sec":98.571429,"type":1},
{"sec":98.571429,"type":1},
{"sec":98.766234,"type":3},
{"sec":98.766234,"type":3},
{"sec":99.155844,"type":1},
{"sec":99.155844,"type":1},
{"sec":99.545455,"type":1},
{"sec":99.74026,"type":1},
{"sec":99.74026,"type":1},
{"sec":99.935065,"type":1},
{"sec":99.935065,"type":1},
{"sec":100.12987,"type":1},
{"sec":100.12987,"type":1},
{"sec":100.324675,"type":2},
{"sec":100.373377,"type":2},
{"sec":100.714286,"type":2},
{"sec":100.762987,"type":2},
{"sec":101.103896,"type":2},
{"sec":101.152597,"type":2},
{"sec":101.201299,"type":2},
{"sec":101.298701,"type":2},
{"sec":101.883117,"type":1},
{"sec":101.980519,"type":1},
{"sec":102.077922,"type":1},
{"sec":102.337662,"type":1},
{"sec":102.337662,"type":1},
{"sec":102.597403,"type":1},
{"sec":102.597403,"type":1},
{"sec":102.857143,"type":3},
{"sec":102.857143,"type":1},
{"sec":103.246753,"type":3},
{"sec":103.441558,"type":1},
{"sec":103.636364,"type":3},
{"sec":104.025974,"type":1},
{"sec":104.220779,"type":1},
{"sec":104.415584,"type":1},
{"sec":105.194805,"type":3},
{"sec":105.194805,"type":1},
{"sec":105.292208,"type":1},
{"sec":105.38961,"type":1},
{"sec":105.487013,"type":1},
{"sec":105.584416,"type":1},
{"sec":105.779221,"type":1},
{"sec":105.974026,"type":1},
{"sec":105.974026,"type":1},
{"sec":106.168831,"type":1},
{"sec":106.363636,"type":1},
{"sec":106.363636,"type":1},
{"sec":106.558442,"type":1},
{"sec":106.558442,"type":1},
{"sec":106.753247,"type":1},
{"sec":106.948052,"type":1},
{"sec":107.142857,"type":1},
{"sec":107.142857,"type":1},
{"sec":107.337662,"type":1},
{"sec":107.532468,"type":1},
{"sec":107.532468,"type":1},
{"sec":107.727273,"type":1},
{"sec":107.727273,"type":1},
{"sec":107.922078,"type":1},
{"sec":108.116883,"type":3},
{"sec":108.116883,"type":1},
{"sec":108.506494,"type":1},
{"sec":108.701299,"type":2},
{"sec":108.75,"type":2},
{"sec":109.090909,"type":1},
{"sec":109.090909,"type":1},
{"sec":109.285714,"type":1},
{"sec":109.480519,"type":1},
{"sec":109.480519,"type":1},
{"sec":109.675325,"type":1},
{"sec":109.675325,"type":1},
{"sec":109.87013,"type":1},
{"sec":110.064935,"type":1},
{"sec":110.25974,"type":1},
{"sec":110.25974,"type":1},
{"sec":110.454545,"type":1},
{"sec":110.649351,"type":1},
{"sec":110.649351,"type":1},
{"sec":110.844156,"type":1},
{"sec":110.844156,"type":1},
{"sec":111.233766,"type":3},
{"sec":111.233766,"type":1},
{"sec":111.623377,"type":1},
{"sec":111.818182,"type":2},
{"sec":111.866883,"type":2},
{"sec":112.207792,"type":3},
{"sec":112.207792,"type":1},
{"sec":112.597403,"type":3},
{"sec":112.597403,"type":3},
{"sec":112.987013,"type":3},
{"sec":112.987013,"type":3},
{"sec":113.376623,"type":1},
{"sec":113.766234,"type":3},
{"sec":113.766234,"type":3},
{"sec":114.155844,"type":1},
{"sec":114.350649,"type":3},
{"sec":114.350649,"type":3},
{"sec":114.74026,"type":1},
{"sec":114.935065,"type":3},
{"sec":114.935065,"type":3},
{"sec":115.324675,"type":3},
{"sec":115.324675,"type":3},
{"sec":115.714286,"type":3},
{"sec":115.714286,"type":3},
{"sec":116.103896,"type":3},
{"sec":116.103896,"type":3},
{"sec":116.493506,"type":1},
{"sec":116.883117,"type":3},
{"sec":116.883117,"type":1},
{"sec":117.142857,"type":1},
{"sec":117.402597,"type":1},
{"sec":117.662338,"type":3},
{"sec":117.662338,"type":3},
{"sec":120.779221,"type":3},
{"sec":123.116883,"type":3},
{"sec":124.675325,"type":1}]