[{"sec":2.463504,"type":2},
{"sec":2.54562,"type":2},
{"sec":2.627737,"type":1},
{"sec":2.846715,"type":1},
{"sec":3.065693,"type":1},
{"sec":3.284672,"type":1},
{"sec":3.50365,"type":1},
{"sec":3.722628,"type":1},
{"sec":3.941606,"type":1},
{"sec":4.160584,"type":1},
{"sec":4.379562,"type":1},
{"sec":4.59854,"type":1},
{"sec":4.817518,"type":1},
{"sec":5.036496,"type":1},
{"sec":5.255474,"type":1},
{"sec":5.474453,"type":1},
{"sec":5.693431,"type":1},
{"sec":5.912409,"type":1},
{"sec":6.131387,"type":1},
{"sec":6.350365,"type":1},
{"sec":6.569343,"type":1},
{"sec":6.788321,"type":1},
{"sec":7.007299,"type":1},
{"sec":7.226277,"type":1},
{"sec":7.445255,"type":1},
{"sec":7.664234,"type":1},
{"sec":7.883212,"type":1},
{"sec":8.10219,"type":1},
{"sec":8.321168,"type":1},
{"sec":8.540146,"type":1},
{"sec":8.759124,"type":1},
{"sec":8.978102,"type":1},
{"sec":9.19708,"type":1},
{"sec":9.416058,"type":1},
{"sec":9.635036,"type":1},
{"sec":9.854015,"type":1},
{"sec":10.072993,"type":3},
{"sec":10.319343,"type":2},
{"sec":10.40146,"type":2},
{"sec":10.510949,"type":3},
{"sec":13.138686,"type":3},
{"sec":13.138686,"type":3},
{"sec":14.014599,"type":1},
{"sec":14.014599,"type":3},
{"sec":14.233577,"type":1},
{"sec":14.452555,"type":1},
{"sec":14.671533,"type":1},
{"sec":14.890511,"type":1},
{"sec":15.109489,"type":1},
{"sec":15.328467,"type":1},
{"sec":16.642336,"type":1},
{"sec":16.861314,"type":1},
{"sec":17.080292,"type":1},
{"sec":17.29927,"type":1},
{"sec":17.518248,"type":1},
{"sec":17.737226,"type":1},
{"sec":17.956204,"type":1},
{"sec":18.394161,"type":3},
{"sec":18.394161,"type":1},
{"sec":18.832117,"type":1},
{"sec":19.270073,"type":1},
{"sec":19.708029,"type":1},
{"sec":19.708029,"type":3},
{"sec":20.145985,"type":1},
{"sec":20.583942,"type":3},
{"sec":20.583942,"type":1},
{"sec":20.80292,"type":2},
{"sec":20.885036,"type":2},
{"sec":20.994526,"type":3},
{"sec":21.021898,"type":3},
{"sec":21.89781,"type":3},
{"sec":22.335766,"type":3},
{"sec":23.649635,"type":3},
{"sec":23.649635,"type":3},
{"sec":24.087591,"type":1},
{"sec":24.525547,"type":1},
{"sec":24.963504,"type":1},
{"sec":25.40146,"type":1},
{"sec":25.839416,"type":1},
{"sec":26.277372,"type":3},
{"sec":27.153285,"type":1},
{"sec":27.153285,"type":3},
{"sec":27.372263,"type":1},
{"sec":27.591241,"type":3},
{"sec":28.467153,"type":3},
{"sec":28.905109,"type":3},
{"sec":29.781022,"type":3},
{"sec":29.781022,"type":1},
{"sec":30.218978,"type":1},
{"sec":30.656934,"type":1},
{"sec":31.094891,"type":1},
{"sec":31.532847,"type":3},
{"sec":32.408759,"type":1},
{"sec":32.408759,"type":3},
{"sec":32.627737,"type":1},
{"sec":32.846715,"type":3},
{"sec":33.284672,"type":3},
{"sec":33.722628,"type":1},
{"sec":33.722628,"type":1},
{"sec":34.160584,"type":3},
{"sec":34.160584,"type":1},
{"sec":34.817518,"type":1},
{"sec":35.036496,"type":1},
{"sec":35.474453,"type":3},
{"sec":35.912409,"type":3},
{"sec":35.912409,"type":3},
{"sec":36.350365,"type":1},
{"sec":36.569343,"type":1},
{"sec":36.788321,"type":3},
{"sec":36.788321,"type":3},
{"sec":37.445255,"type":3},
{"sec":37.664234,"type":1},
{"sec":38.10219,"type":3},
{"sec":38.540146,"type":3},
{"sec":38.540146,"type":3},
{"sec":38.978102,"type":1},
{"sec":39.19708,"type":1},
{"sec":39.416058,"type":3},
{"sec":39.854015,"type":3},
{"sec":40.291971,"type":1},
{"sec":40.510949,"type":1},
{"sec":40.729927,"type":3},
{"sec":41.167883,"type":3},
{"sec":41.605839,"type":1},
{"sec":42.043796,"type":1},
{"sec":42.481752,"type":2},
{"sec":42.536496,"type":2},
{"sec":42.919708,"type":2},
{"sec":42.974453,"type":2},
{"sec":43.357664,"type":2},
{"sec":43.412409,"type":2},
{"sec":43.467153,"type":2},
{"sec":44.233577,"type":2},
{"sec":44.288321,"type":2},
{"sec":44.671533,"type":1},
{"sec":44.890511,"type":1},
{"sec":45.109489,"type":1},
{"sec":45.328467,"type":1},
{"sec":45.547445,"type":1},
{"sec":45.985401,"type":1},
{"sec":45.985401,"type":1},
{"sec":46.423358,"type":1},
{"sec":46.423358,"type":1},
{"sec":46.642336,"type":1},
{"sec":46.861314,"type":1},
{"sec":47.29927,"type":1},
{"sec":47.518248,"type":1},
{"sec":47.737226,"type":1},
{"sec":47.956204,"type":1},
{"sec":48.175182,"type":1},
{"sec":48.613139,"type":1},
{"sec":48.613139,"type":1},
{"sec":48.832117,"type":1},
{"sec":49.051095,"type":1},
{"sec":49.270073,"type":1},
{"sec":49.489051,"type":1},
{"sec":49.927007,"type":3},
{"sec":49.927007,"type":3},
{"sec":50.80292,"type":3},
{"sec":50.80292,"type":3},
{"sec":51.240876,"type":3},
{"sec":51.240876,"type":3},
{"sec":51.678832,"type":3},
{"sec":51.678832,"type":3},
{"sec":52.116788,"type":1},
{"sec":52.116788,"type":1},
{"sec":52.554745,"type":1},
{"sec":52.554745,"type":1},
{"sec":52.992701,"type":1},
{"sec":53.430657,"type":1},
{"sec":53.868613,"type":1},
{"sec":53.868613,"type":1},
{"sec":54.306569,"type":1},
{"sec":54.744526,"type":1},
{"sec":55.182482,"type":3},
{"sec":55.182482,"type":3},
{"sec":55.620438,"type":2},
{"sec":55.675182,"type":2},
{"sec":56.058394,"type":2},
{"sec":56.113139,"type":2},
{"sec":56.49635,"type":3},
{"sec":56.49635,"type":3},
{"sec":56.934307,"type":2},
{"sec":56.989051,"type":2},
{"sec":57.372263,"type":2},
{"sec":57.427007,"type":2},
{"sec":57.810219,"type":3},
{"sec":57.810219,"type":3},
{"sec":58.248175,"type":2},
{"sec":58.30292,"type":2},
{"sec":58.686131,"type":2},
{"sec":58.740876,"type":2},
{"sec":59.124088,"type":3},
{"sec":59.124088,"type":3},
{"sec":59.562044,"type":2},
{"sec":59.616788,"type":2},
{"sec":60,"type":2},
{"sec":60.054745,"type":2},
{"sec":60.437956,"type":3},
{"sec":60.437956,"type":3},
{"sec":60.875912,"type":2},
{"sec":60.930657,"type":2},
{"sec":61.313869,"type":2},
{"sec":61.368613,"type":2},
{"sec":61.751825,"type":3},
{"sec":61.751825,"type":3},
{"sec":62.189781,"type":2},
{"sec":62.244526,"type":2},
{"sec":62.627737,"type":2},
{"sec":62.682482,"type":2},
{"sec":63.065693,"type":3},
{"sec":63.065693,"type":2},
{"sec":63.120438,"type":2},
{"sec":63.722628,"type":1},
{"sec":63.941606,"type":1},
{"sec":64.379562,"type":3},
{"sec":64.379562,"type":2},
{"sec":64.434307,"type":2},
{"sec":64.489051,"type":2},
{"sec":65.255474,"type":1},
{"sec":65.474453,"type":1},
{"sec":65.693431,"type":2},
{"sec":65.693431,"type":3},
{"sec":65.748175,"type":2},
{"sec":66.131387,"type":1},
{"sec":66.569343,"type":3},
{"sec":66.569343,"type":1},
{"sec":67.007299,"type":1},
{"sec":67.007299,"type":1},
{"sec":67.445255,"type":1},
{"sec":67.664234,"type":1},
{"sec":67.883212,"type":1},
{"sec":68.10219,"type":1},
{"sec":68.321168,"type":3},
{"sec":68.321168,"type":1},
{"sec":68.759124,"type":1},
{"sec":69.19708,"type":3},
{"sec":69.19708,"type":1},
{"sec":69.635036,"type":1},
{"sec":69.635036,"type":1},
{"sec":70.072993,"type":1},
{"sec":70.291971,"type":1},
{"sec":70.510949,"type":1},
{"sec":70.729927,"type":1},
{"sec":70.948905,"type":3},
{"sec":70.948905,"type":1},
{"sec":71.386861,"type":1},
{"sec":71.824818,"type":3},
{"sec":71.824818,"type":1},
{"sec":72.262774,"type":1},
{"sec":72.262774,"type":1},
{"sec":72.70073,"type":1},
{"sec":73.138686,"type":1},
{"sec":73.576642,"type":3},
{"sec":73.576642,"type":2},
{"sec":73.631387,"type":2},
{"sec":74.014599,"type":1},
{"sec":74.452555,"type":3},
{"sec":74.452555,"type":1},
{"sec":74.890511,"type":1},
{"sec":74.890511,"type":1},
{"sec":75.328467,"type":1},
{"sec":75.766423,"type":1},
{"sec":75.985401,"type":1},
{"sec":76.20438,"type":1},
{"sec":76.423358,"type":3},
{"sec":76.642336,"type":1},
{"sec":77.080292,"type":1},
{"sec":77.518248,"type":3},
{"sec":77.518248,"type":1},
{"sec":77.956204,"type":1},
{"sec":78.394161,"type":1},
{"sec":78.832117,"type":3},
{"sec":78.832117,"type":3},
{"sec":79.270073,"type":3},
{"sec":79.270073,"type":3},
{"sec":79.708029,"type":1},
{"sec":79.708029,"type":1},
{"sec":80.145985,"type":1},
{"sec":80.145985,"type":1},
{"sec":80.583942,"type":3},
{"sec":80.583942,"type":3},
{"sec":81.459854,"type":2},
{"sec":81.459854,"type":2},
{"sec":81.514599,"type":2},
{"sec":81.514599,"type":2},
{"sec":81.89781,"type":1},
{"sec":82.335766,"type":1},
{"sec":82.773723,"type":1},
{"sec":82.773723,"type":1},
{"sec":83.211679,"type":1},
{"sec":83.649635,"type":1},
{"sec":84.087591,"type":2},
{"sec":84.087591,"type":3},
{"sec":84.142336,"type":2},
{"sec":84.525547,"type":2},
{"sec":84.580292,"type":2},
{"sec":84.963504,"type":2},
{"sec":84.963504,"type":3},
{"sec":85.018248,"type":2},
{"sec":85.182482,"type":1},
{"sec":85.40146,"type":1},
{"sec":85.620438,"type":1},
{"sec":86.058394,"type":1},
{"sec":86.277372,"type":1},
{"sec":86.49635,"type":1},
{"sec":86.715328,"type":1},
{"sec":86.934307,"type":3},
{"sec":87.153285,"type":3},
{"sec":87.591241,"type":1},
{"sec":88.029197,"type":1},
{"sec":88.467153,"type":1},
{"sec":88.905109,"type":1},
{"sec":89.343066,"type":3},
{"sec":90.218978,"type":1},
{"sec":90.218978,"type":3},
{"sec":90.656934,"type":1},
{"sec":91.094891,"type":1},
{"sec":91.532847,"type":1},
{"sec":91.751825,"type":1},
{"sec":91.970803,"type":3},
{"sec":91.970803,"type":3},
{"sec":93.284672,"type":3},
{"sec":93.722628,"type":1},
{"sec":93.941606,"type":1},
{"sec":94.160584,"type":1},
{"sec":94.379562,"type":1},
{"sec":94.59854,"type":3},
{"sec":95.474453,"type":3},
{"sec":95.912409,"type":1},
{"sec":96.350365,"type":1},
{"sec":96.569343,"type":1},
{"sec":96.788321,"type":1},
{"sec":97.007299,"type":1},
{"sec":97.226277,"type":3},
{"sec":98.10219,"type":3},
{"sec":98.10219,"type":3},
{"sec":98.540146,"type":1},
{"sec":98.978102,"type":2},
{"sec":99.032847,"type":2},
{"sec":99.416058,"type":2},
{"sec":99.470803,"type":2},
{"sec":99.854015,"type":2},
{"sec":99.908759,"type":2},
{"sec":100.291971,"type":1},
{"sec":100.729927,"type":1},
{"sec":101.167883,"type":1},
{"sec":101.167883,"type":1},
{"sec":101.605839,"type":1},
{"sec":102.043796,"type":1},
{"sec":102.262774,"type":1},
{"sec":102.481752,"type":1},
{"sec":102.70073,"type":1},
{"sec":102.919708,"type":1},
{"sec":103.357664,"type":1},
{"sec":103.79562,"type":1},
{"sec":103.79562,"type":1},
{"sec":104.233577,"type":1},
{"sec":104.671533,"type":1},
{"sec":105.109489,"type":1},
{"sec":105.109489,"type":1},
{"sec":105.547445,"type":1},
{"sec":105.985401,"type":1},
{"sec":106.423358,"type":1},
{"sec":106.423358,"type":1},
{"sec":106.861314,"type":1},
{"sec":107.737226,"type":2},
{"sec":107.737226,"type":2},
{"sec":107.791971,"type":2},
{"sec":107.791971,"type":2},
{"sec":108.175182,"type":1},
{"sec":108.613139,"type":1},
{"sec":109.051095,"type":1},
{"sec":109.051095,"type":1},
{"sec":109.489051,"type":1},
{"sec":109.927007,"type":1},
{"sec":110.364964,"type":3},
{"sec":110.364964,"type":2},
{"sec":110.419708,"type":2},
{"sec":110.80292,"type":2},
{"sec":110.857664,"type":2},
{"sec":111.240876,"type":3},
{"sec":111.240876,"type":2},
{"sec":111.29562,"type":2},
{"sec":111.459854,"type":1},
{"sec":111.678832,"type":1},
{"sec":111.89781,"type":1},
{"sec":112.335766,"type":1},
{"sec":112.554745,"type":1},
{"sec":112.773723,"type":1},
{"sec":112.992701,"type":1},
{"sec":113.211679,"type":3},
{"sec":114.279197,"type":3},
{"sec":115.182482,"type":3},
{"sec":115.620438,"type":3},
{"sec":116.49635,"type":3},
{"sec":116.85219,"type":3},
{"sec":118.248175,"type":3},
{"sec":118.959854,"type":2},
{"sec":118.99635,"type":2},
{"sec":119.096715,"type":3},
{"sec":119.917883,"type":3},
{"sec":122.627737,"type":3},
{"sec":122.627737,"type":3},
{"sec":125.255474,"type":1}]