[
{"sec":1.875,"type":2},
{"sec":1.933594,"type":2},
{"sec":2.109375,"type":2},
{"sec":2.226563,"type":2},
{"sec":2.285156,"type":2},
{"sec":2.460938,"type":2},
{"sec":2.578125,"type":2},
{"sec":2.695313,"type":2},
{"sec":2.8125,"type":3},
{"sec":2.929688,"type":3},
{"sec":3.046875,"type":3},
{"sec":3.164063,"type":3},
{"sec":3.28125,"type":3},
{"sec":3.515625,"type":3},
{"sec":3.515625,"type":3},
{"sec":3.75,"type":3},
{"sec":3.75,"type":2},
{"sec":3.808594,"type":2},
{"sec":3.984375,"type":2},
{"sec":4.101563,"type":2},
{"sec":4.160156,"type":2},
{"sec":4.335938,"type":2},
{"sec":4.453125,"type":2},
{"sec":4.570313,"type":2},
{"sec":4.6875,"type":2},
{"sec":4.746094,"type":2},
{"sec":4.921875,"type":2},
{"sec":5.039063,"type":2},
{"sec":5.097656,"type":2},
{"sec":5.15625,"type":3},
{"sec":5.390625,"type":3},
{"sec":5.390625,"type":3},
{"sec":5.625,"type":3},
{"sec":5.625,"type":2},
{"sec":5.683594,"type":2},
{"sec":5.859375,"type":2},
{"sec":5.976563,"type":2},
{"sec":6.035156,"type":2},
{"sec":6.210938,"type":2},
{"sec":6.328125,"type":2},
{"sec":6.445313,"type":2},
{"sec":6.5625,"type":3},
{"sec":6.679688,"type":3},
{"sec":6.796875,"type":3},
{"sec":6.914063,"type":3},
{"sec":7.03125,"type":3},
{"sec":7.265625,"type":3},
{"sec":7.265625,"type":3},
{"sec":7.5,"type":3},
{"sec":7.5,"type":2},
{"sec":7.558594,"type":2},
{"sec":7.734375,"type":2},
{"sec":7.851563,"type":2},
{"sec":7.910156,"type":2},
{"sec":8.085938,"type":2},
{"sec":8.203125,"type":2},
{"sec":8.320313,"type":2},
{"sec":8.4375,"type":2},
{"sec":8.554688,"type":2},
{"sec":8.90625,"type":2},
{"sec":9.023438,"type":2},
{"sec":9.375,"type":2},
{"sec":9.375,"type":2},
{"sec":9.433594,"type":2},
{"sec":9.609375,"type":2},
{"sec":9.726563,"type":2},
{"sec":9.960938,"type":2},
{"sec":10.078125,"type":2},
{"sec":10.3125,"type":2},
{"sec":10.429688,"type":2},
{"sec":10.546875,"type":2},
{"sec":10.664063,"type":2},
{"sec":10.78125,"type":2},
{"sec":10.898438,"type":2},
{"sec":11.015625,"type":2},
{"sec":11.25,"type":2},
{"sec":11.484375,"type":2},
{"sec":11.601563,"type":2},
{"sec":11.835938,"type":2},
{"sec":11.953125,"type":2},
{"sec":12.1875,"type":2},
{"sec":12.304688,"type":2},
{"sec":12.421875,"type":2},
{"sec":12.539063,"type":2},
{"sec":12.65625,"type":2},
{"sec":12.773438,"type":2},
{"sec":12.890625,"type":2},
{"sec":13.125,"type":2},
{"sec":13.359375,"type":2},
{"sec":13.476563,"type":2},
{"sec":13.710938,"type":2},
{"sec":13.828125,"type":2},
{"sec":14.0625,"type":2},
{"sec":14.179688,"type":2},
{"sec":14.296875,"type":2},
{"sec":14.414063,"type":2},
{"sec":14.53125,"type":2},
{"sec":14.648438,"type":2},
{"sec":14.765625,"type":2},
{"sec":15,"type":2},
{"sec":15.234375,"type":2},
{"sec":15.351563,"type":2},
{"sec":15.585938,"type":2},
{"sec":15.703125,"type":2},
{"sec":15.9375,"type":2},
{"sec":16.054688,"type":2},
{"sec":16.171875,"type":2},
{"sec":16.289063,"type":2},
{"sec":16.40625,"type":2},
{"sec":16.523438,"type":2},
{"sec":16.640625,"type":2},
{"sec":16.875,"type":2},
{"sec":16.875,"type":2},
{"sec":16.933594,"type":2},
{"sec":17.109375,"type":2},
{"sec":17.226563,"type":2},
{"sec":17.460938,"type":2},
{"sec":17.578125,"type":2},
{"sec":17.8125,"type":2},
{"sec":17.929688,"type":2},
{"sec":18.046875,"type":2},
{"sec":18.164063,"type":2},
{"sec":18.28125,"type":2},
{"sec":18.398438,"type":2},
{"sec":18.515625,"type":2},
{"sec":18.75,"type":2},
{"sec":18.984375,"type":2},
{"sec":19.101563,"type":2},
{"sec":19.335938,"type":2},
{"sec":19.453125,"type":2},
{"sec":19.6875,"type":2},
{"sec":19.804688,"type":2},
{"sec":19.921875,"type":2},
{"sec":20.039063,"type":2},
{"sec":20.15625,"type":2},
{"sec":20.273438,"type":2},
{"sec":20.390625,"type":2},
{"sec":20.625,"type":2},
{"sec":20.859375,"type":2},
{"sec":20.976563,"type":2},
{"sec":21.210938,"type":2},
{"sec":21.328125,"type":2},
{"sec":21.5625,"type":2},
{"sec":21.679688,"type":2},
{"sec":21.796875,"type":2},
{"sec":21.914063,"type":2},
{"sec":22.03125,"type":2},
{"sec":22.148438,"type":2},
{"sec":22.265625,"type":2},
{"sec":22.5,"type":2},
{"sec":22.617188,"type":2},
{"sec":22.734375,"type":2},
{"sec":22.851563,"type":2},
{"sec":23.203125,"type":2},
{"sec":23.320313,"type":2},
{"sec":23.4375,"type":2},
{"sec":23.554688,"type":2},
{"sec":24.375,"type":3},
{"sec":24.375,"type":2},
{"sec":24.433594,"type":2},
{"sec":25.3125,"type":3},
{"sec":25.78125,"type":2},
{"sec":26.015625,"type":2},
{"sec":26.25,"type":3},
{"sec":26.484375,"type":2},
{"sec":26.601563,"type":2},
{"sec":26.953125,"type":2},
{"sec":27.1875,"type":2},
{"sec":27.65625,"type":2},
{"sec":28.125,"type":3},
{"sec":29.0625,"type":3},
{"sec":29.53125,"type":2},
{"sec":30,"type":2},
{"sec":30.351563,"type":2},
{"sec":30.703125,"type":2},
{"sec":30.9375,"type":2},
{"sec":31.40625,"type":2},
{"sec":31.875,"type":3},
{"sec":31.875,"type":2},
{"sec":31.933594,"type":2},
{"sec":32.226563,"type":2},
{"sec":32.578125,"type":2},
{"sec":32.8125,"type":3},
{"sec":32.929688,"type":2},
{"sec":33.28125,"type":2},
{"sec":33.28125,"type":2},
{"sec":33.515625,"type":2},
{"sec":33.515625,"type":2},
{"sec":33.75,"type":2},
{"sec":33.75,"type":2},
{"sec":34.101563,"type":2},
{"sec":34.101563,"type":2},
{"sec":34.453125,"type":2},
{"sec":34.453125,"type":2},
{"sec":34.6875,"type":2},
{"sec":34.804688,"type":2},
{"sec":35.15625,"type":2},
{"sec":35.15625,"type":2},
{"sec":35.625,"type":2},
{"sec":35.625,"type":3},
{"sec":35.976563,"type":2},
{"sec":36.328125,"type":2},
{"sec":36.5625,"type":3},
{"sec":36.679688,"type":2},
{"sec":37.03125,"type":2},
{"sec":37.03125,"type":2},
{"sec":37.5,"type":2},
{"sec":37.5,"type":2},
{"sec":37.851563,"type":2},
{"sec":37.96875,"type":2},
{"sec":38.203125,"type":2},
{"sec":38.320313,"type":2},
{"sec":38.4375,"type":2},
{"sec":38.554688,"type":2},
{"sec":38.671875,"type":2},
{"sec":38.789063,"type":2},
{"sec":38.90625,"type":2},
{"sec":39.375,"type":3},
{"sec":39.375,"type":2},
{"sec":39.609375,"type":2},
{"sec":39.667969,"type":2},
{"sec":40.078125,"type":2},
{"sec":40.3125,"type":3},
{"sec":40.3125,"type":2},
{"sec":40.371094,"type":2},
{"sec":40.78125,"type":2},
{"sec":41.015625,"type":2},
{"sec":41.25,"type":2},
{"sec":41.25,"type":2},
{"sec":41.484375,"type":2},
{"sec":41.542969,"type":2},
{"sec":41.601563,"type":2},
{"sec":41.953125,"type":2},
{"sec":41.953125,"type":2},
{"sec":42.1875,"type":2},
{"sec":42.1875,"type":2},
{"sec":42.246094,"type":2},
{"sec":42.65625,"type":2},
{"sec":43.125,"type":2},
{"sec":43.125,"type":3},
{"sec":43.359375,"type":2},
{"sec":43.417969,"type":2},
{"sec":43.828125,"type":2},
{"sec":44.0625,"type":2},
{"sec":44.0625,"type":3},
{"sec":44.121094,"type":2},
{"sec":44.53125,"type":2},
{"sec":44.765625,"type":2},
{"sec":45,"type":2},
{"sec":45,"type":2},
{"sec":45.234375,"type":2},
{"sec":45.292969,"type":2},
{"sec":45.351563,"type":2},
{"sec":45.703125,"type":2},
{"sec":45.703125,"type":2},
{"sec":45.9375,"type":2},
{"sec":45.9375,"type":2},
{"sec":45.996094,"type":2},
{"sec":46.40625,"type":2},
{"sec":46.40625,"type":2},
{"sec":46.875,"type":3},
{"sec":46.875,"type":2},
{"sec":47.109375,"type":2},
{"sec":47.167969,"type":2},
{"sec":47.578125,"type":2},
{"sec":47.8125,"type":3},
{"sec":47.8125,"type":2},
{"sec":47.871094,"type":2},
{"sec":48.28125,"type":2},
{"sec":48.339844,"type":2},
{"sec":48.427734,"type":2},
{"sec":48.75,"type":2},
{"sec":48.808594,"type":2},
{"sec":48.896484,"type":2},
{"sec":49.101563,"type":2},
{"sec":49.101563,"type":2},
{"sec":49.453125,"type":2},
{"sec":49.6875,"type":3},
{"sec":49.921875,"type":3},
{"sec":50.15625,"type":2},
{"sec":50.15625,"type":2},
{"sec":50.214844,"type":2},
{"sec":50.625,"type":3},
{"sec":50.625,"type":2},
{"sec":50.683594,"type":2},
{"sec":50.859375,"type":2},
{"sec":51.09375,"type":2},
{"sec":51.09375,"type":3},
{"sec":51.328125,"type":2},
{"sec":51.328125,"type":2},
{"sec":51.5625,"type":2},
{"sec":51.5625,"type":3},
{"sec":51.796875,"type":2},
{"sec":52.03125,"type":2},
{"sec":52.03125,"type":3},
{"sec":52.265625,"type":2},
{"sec":52.5,"type":2},
{"sec":52.5,"type":2},
{"sec":52.851563,"type":2},
{"sec":52.851563,"type":2},
{"sec":53.203125,"type":3},
{"sec":53.203125,"type":3},
{"sec":53.4375,"type":2},
{"sec":53.4375,"type":2},
{"sec":53.496094,"type":2},
{"sec":53.496094,"type":2},
{"sec":53.90625,"type":3},
{"sec":53.90625,"type":2},
{"sec":54.375,"type":2},
{"sec":54.375,"type":2},
{"sec":54.433594,"type":2},
{"sec":54.609375,"type":2},
{"sec":54.726563,"type":2},
{"sec":54.960938,"type":2},
{"sec":55.078125,"type":3},
{"sec":55.3125,"type":2},
{"sec":55.3125,"type":2},
{"sec":55.371094,"type":2},
{"sec":55.546875,"type":2},
{"sec":55.664063,"type":2},
{"sec":55.898438,"type":3},
{"sec":56.015625,"type":3},
{"sec":56.25,"type":2},
{"sec":56.25,"type":2},
{"sec":56.367188,"type":2},
{"sec":56.367188,"type":2},
{"sec":56.601563,"type":2},
{"sec":56.630859,"type":2},
{"sec":56.660156,"type":2},
{"sec":56.689453,"type":2},
{"sec":56.777344,"type":2},
{"sec":56.953125,"type":2},
{"sec":57.011719,"type":2},
{"sec":57.1875,"type":2},
{"sec":57.216797,"type":2},
{"sec":57.275391,"type":2},
{"sec":57.363281,"type":2},
{"sec":57.65625,"type":2},
{"sec":57.65625,"type":2},
{"sec":57.890625,"type":2},
{"sec":58.125,"type":2},
{"sec":58.125,"type":2},
{"sec":58.359375,"type":2},
{"sec":58.476563,"type":2},
{"sec":58.476563,"type":2},
{"sec":58.828125,"type":2},
{"sec":58.828125,"type":2},
{"sec":59.0625,"type":2},
{"sec":59.0625,"type":2},
{"sec":59.296875,"type":2},
{"sec":59.414063,"type":2},
{"sec":59.414063,"type":2},
{"sec":59.765625,"type":2},
{"sec":59.765625,"type":2},
{"sec":60,"type":2},
{"sec":60,"type":2},
{"sec":60.234375,"type":2},
{"sec":60.351563,"type":3},
{"sec":60.351563,"type":2},
{"sec":60.703125,"type":2},
{"sec":61.171875,"type":2},
{"sec":61.171875,"type":3},
{"sec":61.640625,"type":3},
{"sec":61.845703,"type":2},
{"sec":61.875,"type":2},
{"sec":61.904297,"type":2},
{"sec":61.933594,"type":2},
{"sec":61.962891,"type":2},
{"sec":62.109375,"type":2},
{"sec":62.226563,"type":2},
{"sec":62.460938,"type":2},
{"sec":62.578125,"type":3},
{"sec":62.783203,"type":2},
{"sec":62.8125,"type":2},
{"sec":62.841797,"type":2},
{"sec":62.871094,"type":2},
{"sec":62.900391,"type":2},
{"sec":63.046875,"type":2},
{"sec":63.164063,"type":2},
{"sec":63.398438,"type":2},
{"sec":63.515625,"type":3},
{"sec":63.75,"type":3},
{"sec":64.101563,"type":2},
{"sec":64.101563,"type":2},
{"sec":64.453125,"type":2},
{"sec":64.453125,"type":2},
{"sec":64.511719,"type":2},
{"sec":64.511719,"type":2},
{"sec":64.6875,"type":2},
{"sec":64.6875,"type":2},
{"sec":64.746094,"type":2},
{"sec":64.746094,"type":2},
{"sec":65.15625,"type":3},
{"sec":65.390625,"type":3},
{"sec":65.625,"type":2},
{"sec":65.625,"type":2},
{"sec":65.859375,"type":2},
{"sec":65.976563,"type":2},
{"sec":65.976563,"type":2},
{"sec":66.328125,"type":2},
{"sec":66.328125,"type":2},
{"sec":66.5625,"type":2},
{"sec":66.5625,"type":2},
{"sec":66.796875,"type":2},
{"sec":66.914063,"type":2},
{"sec":66.914063,"type":2},
{"sec":67.265625,"type":2},
{"sec":67.265625,"type":2},
{"sec":67.5,"type":2},
{"sec":67.5,"type":2},
{"sec":67.734375,"type":2},
{"sec":67.851563,"type":3},
{"sec":67.851563,"type":2},
{"sec":68.203125,"type":2},
{"sec":68.671875,"type":3},
{"sec":68.671875,"type":2},
{"sec":68.90625,"type":2},
{"sec":69.023438,"type":2},
{"sec":69.140625,"type":2},
{"sec":69.257813,"type":2},
{"sec":69.375,"type":2},
{"sec":69.433594,"type":2},
{"sec":69.726563,"type":2},
{"sec":69.726563,"type":2},
{"sec":70.078125,"type":2},
{"sec":70.078125,"type":2},
{"sec":70.3125,"type":2},
{"sec":70.3125,"type":2},
{"sec":70.664063,"type":2},
{"sec":70.664063,"type":2},
{"sec":71.015625,"type":2},
{"sec":71.015625,"type":2},
{"sec":71.25,"type":2},
{"sec":71.25,"type":2},
{"sec":71.601563,"type":3},
{"sec":71.601563,"type":2},
{"sec":71.953125,"type":3},
{"sec":72.070313,"type":3},
{"sec":72.1875,"type":3},
{"sec":72.304688,"type":3},
{"sec":72.421875,"type":3},
{"sec":72.539063,"type":3},
{"sec":72.65625,"type":3},
{"sec":72.773438,"type":3},
{"sec":72.890625,"type":3},
{"sec":73.007813,"type":3},
{"sec":73.125,"type":3},
{"sec":73.125,"type":3},
{"sec":73.359375,"type":2},
{"sec":73.476563,"type":2},
{"sec":73.59375,"type":3},
{"sec":73.828125,"type":2},
{"sec":73.945313,"type":2},
{"sec":74.0625,"type":3},
{"sec":74.414063,"type":3},
{"sec":74.414063,"type":2},
{"sec":74.53125,"type":2},
{"sec":74.765625,"type":2},
{"sec":75,"type":3},
{"sec":75.703125,"type":3},
{"sec":75.703125,"type":2},
{"sec":75.9375,"type":2},
{"sec":76.054688,"type":3},
{"sec":76.289063,"type":3},
{"sec":76.289063,"type":2},
{"sec":76.640625,"type":2},
{"sec":76.875,"type":3},
{"sec":77.226563,"type":3},
{"sec":77.226563,"type":3},
{"sec":77.578125,"type":3},
{"sec":77.578125,"type":3},
{"sec":77.8125,"type":3},
{"sec":77.8125,"type":3},
{"sec":78.515625,"type":3},
{"sec":78.515625,"type":2},
{"sec":78.632813,"type":2},
{"sec":78.75,"type":2},
{"sec":78.867188,"type":2},
{"sec":78.984375,"type":2},
{"sec":79.101563,"type":2},
{"sec":79.21875,"type":2},
{"sec":79.453125,"type":2},
{"sec":79.570313,"type":2},
{"sec":79.6875,"type":2},
{"sec":79.804688,"type":2},
{"sec":79.921875,"type":2},
{"sec":80.039063,"type":2},
{"sec":80.15625,"type":2},
{"sec":80.273438,"type":2},
{"sec":80.390625,"type":2},
{"sec":80.507813,"type":2},
{"sec":80.625,"type":3},
{"sec":81.09375,"type":3},
{"sec":81.09375,"type":2},
{"sec":81.328125,"type":2},
{"sec":81.5625,"type":3},
{"sec":81.914063,"type":3},
{"sec":81.914063,"type":3},
{"sec":82.265625,"type":3},
{"sec":82.265625,"type":3},
{"sec":82.5,"type":3},
{"sec":82.5,"type":2},
{"sec":82.96875,"type":3},
{"sec":82.96875,"type":3},
{"sec":83.90625,"type":3},
{"sec":83.90625,"type":3},
{"sec":84.023438,"type":2},
{"sec":84.140625,"type":2},
{"sec":84.257813,"type":2},
{"sec":84.375,"type":2},
{"sec":84.433594,"type":2},
{"sec":84.726563,"type":2},
{"sec":84.726563,"type":2},
{"sec":85.078125,"type":2},
{"sec":85.078125,"type":2},
{"sec":85.3125,"type":2},
{"sec":85.3125,"type":3},
{"sec":85.78125,"type":3},
{"sec":85.78125,"type":3},
{"sec":86.015625,"type":3},
{"sec":86.25,"type":2},
{"sec":86.25,"type":3},
{"sec":86.308594,"type":2},
{"sec":86.484375,"type":2},
{"sec":86.601563,"type":2},
{"sec":86.835938,"type":2},
{"sec":86.953125,"type":2},
{"sec":87.1875,"type":3},
{"sec":87.1875,"type":2},
{"sec":87.65625,"type":2},
{"sec":87.890625,"type":3},
{"sec":88.125,"type":3},
{"sec":88.125,"type":3},
{"sec":88.59375,"type":3},
{"sec":88.828125,"type":3},
{"sec":88.828125,"type":2},
{"sec":89.0625,"type":3},
{"sec":89.0625,"type":2},
{"sec":89.121094,"type":2},
{"sec":89.414063,"type":2},
{"sec":89.414063,"type":3},
{"sec":89.472656,"type":2},
{"sec":89.765625,"type":2},
{"sec":89.765625,"type":3},
{"sec":89.824219,"type":2},
{"sec":90,"type":2},
{"sec":90.029297,"type":2},
{"sec":90.058594,"type":2},
{"sec":90.087891,"type":2},
{"sec":90.351563,"type":2},
{"sec":90.410156,"type":2},
{"sec":90.498047,"type":2},
{"sec":90.703125,"type":2},
{"sec":90.732422,"type":2},
{"sec":90.761719,"type":2},
{"sec":90.791016,"type":2},
{"sec":90.9375,"type":2},
{"sec":90.966797,"type":2},
{"sec":90.996094,"type":2},
{"sec":91.025391,"type":2},
{"sec":91.083984,"type":2},
{"sec":91.40625,"type":3},
{"sec":91.640625,"type":3},
{"sec":91.875,"type":2},
{"sec":91.875,"type":2},
{"sec":92.109375,"type":2},
{"sec":92.226563,"type":2},
{"sec":92.226563,"type":2},
{"sec":92.578125,"type":2},
{"sec":92.578125,"type":2},
{"sec":92.8125,"type":2},
{"sec":92.8125,"type":2},
{"sec":93.046875,"type":2},
{"sec":93.164063,"type":2},
{"sec":93.164063,"type":2},
{"sec":93.515625,"type":2},
{"sec":93.515625,"type":2},
{"sec":93.75,"type":2},
{"sec":93.75,"type":2},
{"sec":93.984375,"type":2},
{"sec":94.101563,"type":3},
{"sec":94.101563,"type":2},
{"sec":94.453125,"type":2},
{"sec":94.921875,"type":2},
{"sec":94.921875,"type":3},
{"sec":95.390625,"type":3},
{"sec":95.595703,"type":2},
{"sec":95.625,"type":2},
{"sec":95.654297,"type":2},
{"sec":95.683594,"type":2},
{"sec":95.712891,"type":2},
{"sec":95.859375,"type":2},
{"sec":95.976563,"type":2},
{"sec":96.210938,"type":2},
{"sec":96.328125,"type":3},
{"sec":96.533203,"type":2},
{"sec":96.5625,"type":2},
{"sec":96.591797,"type":2},
{"sec":96.621094,"type":2},
{"sec":96.650391,"type":2},
{"sec":96.796875,"type":2},
{"sec":96.914063,"type":2},
{"sec":97.148438,"type":2},
{"sec":97.265625,"type":2},
{"sec":97.5,"type":3},
{"sec":97.851563,"type":3},
{"sec":98.203125,"type":2},
{"sec":98.203125,"type":2},
{"sec":98.4375,"type":2},
{"sec":98.4375,"type":2},
{"sec":98.496094,"type":2},
{"sec":98.496094,"type":2},
{"sec":98.90625,"type":3},
{"sec":99.140625,"type":3},
{"sec":99.375,"type":2},
{"sec":99.375,"type":2},
{"sec":99.609375,"type":2},
{"sec":99.726563,"type":2},
{"sec":99.726563,"type":2},
{"sec":100.078125,"type":2},
{"sec":100.078125,"type":2},
{"sec":100.3125,"type":2},
{"sec":100.3125,"type":2},
{"sec":100.546875,"type":2},
{"sec":100.664063,"type":2},
{"sec":100.664063,"type":2},
{"sec":101.015625,"type":2},
{"sec":101.015625,"type":2},
{"sec":101.25,"type":2},
{"sec":101.25,"type":2},
{"sec":101.484375,"type":2},
{"sec":101.601563,"type":2},
{"sec":101.601563,"type":3},
{"sec":101.953125,"type":2},
{"sec":102.421875,"type":3},
{"sec":102.421875,"type":2},
{"sec":102.65625,"type":2},
{"sec":102.773438,"type":2},
{"sec":102.890625,"type":2},
{"sec":103.007813,"type":2},
{"sec":103.125,"type":2},
{"sec":103.183594,"type":2},
{"sec":103.476563,"type":2},
{"sec":103.476563,"type":2},
{"sec":103.828125,"type":2},
{"sec":103.828125,"type":2},
{"sec":104.0625,"type":2},
{"sec":104.0625,"type":2},
{"sec":104.414063,"type":2},
{"sec":104.414063,"type":2},
{"sec":104.765625,"type":2},
{"sec":104.765625,"type":2},
{"sec":105,"type":3},
{"sec":105,"type":2},
{"sec":105.058594,"type":2},
{"sec":105.351563,"type":3},
{"sec":106.640625,"type":3},
{"sec":106.640625,"type":3},
{"sec":106.875,"type":3},
{"sec":107.109375,"type":3},
{"sec":107.109375,"type":2},
{"sec":107.226563,"type":3},
{"sec":107.460938,"type":3},
{"sec":107.460938,"type":2},
{"sec":107.578125,"type":2},
{"sec":107.695313,"type":2},
{"sec":107.8125,"type":2},
{"sec":107.929688,"type":2},
{"sec":108.046875,"type":2},
{"sec":108.164063,"type":2},
{"sec":108.28125,"type":3},
{"sec":108.515625,"type":2},
{"sec":108.574219,"type":2},
{"sec":108.75,"type":3},
{"sec":108.984375,"type":2},
{"sec":108.984375,"type":3},
{"sec":109.101563,"type":3},
{"sec":109.335938,"type":3},
{"sec":109.335938,"type":2},
{"sec":109.453125,"type":2},
{"sec":109.570313,"type":2},
{"sec":109.6875,"type":2},
{"sec":109.804688,"type":2},
{"sec":109.921875,"type":2},
{"sec":110.039063,"type":2},
{"sec":110.15625,"type":3},
{"sec":110.390625,"type":2},
{"sec":110.449219,"type":2},
{"sec":110.625,"type":3},
{"sec":110.859375,"type":2},
{"sec":110.859375,"type":3},
{"sec":110.976563,"type":3},
{"sec":111.210938,"type":3},
{"sec":111.210938,"type":2},
{"sec":111.328125,"type":2},
{"sec":111.445313,"type":2},
{"sec":111.5625,"type":2},
{"sec":111.679688,"type":2},
{"sec":111.796875,"type":2},
{"sec":111.914063,"type":2},
{"sec":112.03125,"type":3},
{"sec":112.265625,"type":2},
{"sec":112.324219,"type":2},
{"sec":112.5,"type":2},
{"sec":112.558594,"type":2},
{"sec":112.734375,"type":2},
{"sec":112.851563,"type":3},
{"sec":113.085938,"type":3},
{"sec":113.085938,"type":2},
{"sec":113.203125,"type":2},
{"sec":113.320313,"type":2},
{"sec":113.4375,"type":2},
{"sec":113.554688,"type":2},
{"sec":113.671875,"type":2},
{"sec":113.789063,"type":2},
{"sec":113.90625,"type":3},
{"sec":114.140625,"type":2},
{"sec":114.199219,"type":2},
{"sec":114.375,"type":3},
{"sec":114.609375,"type":2},
{"sec":114.609375,"type":3},
{"sec":114.726563,"type":3},
{"sec":114.960938,"type":3},
{"sec":114.960938,"type":2},
{"sec":115.078125,"type":2},
{"sec":115.195313,"type":2},
{"sec":115.3125,"type":2},
{"sec":115.429688,"type":2},
{"sec":115.546875,"type":2},
{"sec":115.664063,"type":2},
{"sec":115.78125,"type":3},
{"sec":116.015625,"type":2},
{"sec":116.074219,"type":2},
{"sec":116.25,"type":3},
{"sec":116.484375,"type":2},
{"sec":116.484375,"type":3},
{"sec":116.601563,"type":3},
{"sec":116.835938,"type":3},
{"sec":116.835938,"type":2},
{"sec":116.953125,"type":2},
{"sec":117.070313,"type":2},
{"sec":117.1875,"type":2},
{"sec":117.304688,"type":2},
{"sec":117.421875,"type":2},
{"sec":117.539063,"type":2},
{"sec":117.65625,"type":3},
{"sec":117.890625,"type":2},
{"sec":117.949219,"type":2},
{"sec":118.125,"type":2},
{"sec":118.242188,"type":2},
{"sec":118.359375,"type":2},
{"sec":118.476563,"type":2},
{"sec":118.828125,"type":2},
{"sec":118.886719,"type":2},
{"sec":118.945313,"type":2},
{"sec":119.0625,"type":2},
{"sec":119.179688,"type":2},
{"sec":121.875,"type":2}]
